http_gob_operator/__init__.py
http_gob_operator/http_gob_operator.py
amsterdam_airflow_http_gob_operator-1.3.dist-info/METADATA
amsterdam_airflow_http_gob_operator-1.3.dist-info/WHEEL
amsterdam_airflow_http_gob_operator-1.3.dist-info/RECORD
